pyckles/__init__.py
pyckles/codegen.py
pyckles/defaults.py
pyckles/freckles_cli_plugin_codegen.py
pyckles/freckles_utils.py
pyckles/frkl.info
pyckles/pyckles.py
pyckles/utils.py
pyckles/contexts/__init__.py
pyckles/contexts/freck.py
pyckles/contexts/python.py
pyckles/external/freck/freck
frkl.pyckles-1.0.1.dist-info/AUTHORS.rst
frkl.pyckles-1.0.1.dist-info/LICENSE
frkl.pyckles-1.0.1.dist-info/METADATA
frkl.pyckles-1.0.1.dist-info/WHEEL
frkl.pyckles-1.0.1.dist-info/entry_points.txt
frkl.pyckles-1.0.1.dist-info/top_level.txt
frkl.pyckles-1.0.1.dist-info/RECORD
